cdk_att_projen_awscdk_construct/__init__.py
cdk_att_projen_awscdk_construct/py.typed
cdk_att_projen_awscdk_construct/_jsii/__init__.py
cdk_att_projen_awscdk_construct/_jsii/projen-awscdk-construct@0.0.4.jsii.tgz
cdk_att.projen_awscdk_construct-0.0.4.dist-info/LICENSE
cdk_att.projen_awscdk_construct-0.0.4.dist-info/METADATA
cdk_att.projen_awscdk_construct-0.0.4.dist-info/WHEEL
cdk_att.projen_awscdk_construct-0.0.4.dist-info/top_level.txt
cdk_att.projen_awscdk_construct-0.0.4.dist-info/RECORD
