Metadata-Version: 2.1
Name: cdk-att.projen-awscdk-construct
Version: 0.0.4
Summary: @cdk-att/projen-awscdk-construct
Home-page: https://github.com/rridgley/projen-awscdk-construct.git
Author: Randy Ridgley<randy.ridgley@gmail.com>
License: Apache-2.0
Project-URL: Source, https://github.com/rridgley/projen-awscdk-construct.git
Classifier: Intended Audience :: Developers
Classifier: Operating System :: OS Independent
Classifier: Programming Language :: JavaScript
Classifier: Programming Language :: Python :: 3 :: Only
Classifier: Programming Language :: Python :: 3.8
Classifier: Programming Language :: Python :: 3.9
Classifier: Programming Language :: Python :: 3.10
Classifier: Programming Language :: Python :: 3.11
Classifier: Typing :: Typed
Classifier: Development Status :: 5 - Production/Stable
Classifier: License :: OSI Approved
Requires-Python: ~=3.8
License-File: LICENSE
Requires-Dist: aws-cdk-lib <3.0.0,>=2.99.0
Requires-Dist: aws-cdk.aws-apigatewayv2-alpha <3.0.0,>=2.99.0.a0
Requires-Dist: aws-cdk.aws-redshift-alpha <3.0.0,>=2.99.0.a0
Requires-Dist: cdk-monitoring-constructs <7.0.0,>=6.0.0
Requires-Dist: cdk-nag <3.0.0,>=2.27.0
Requires-Dist: constructs <11.0.0,>=10.3.0
Requires-Dist: jsii <2.0.0,>=1.92.0
Requires-Dist: projen <0.78.0,>=0.77.1
Requires-Dist: publication >=0.0.3
Requires-Dist: typeguard ~=2.13.3
